HomeveeCloud/__init__.py
HomeveeCloud/command_line.py
HomeveeCloud/firebase_utils.py
HomeveeCloud/socket_utils.py
HomeveeCloudLegacy/__init__.py
HomeveeCloudLegacy/firebase_utils.py
HomeveeCloudLegacy/https_server.py
HomeveeCloudLegacy/oauth-test.py
HomeveeCloudLegacy/socket_utils.py
Homevee_Cloud-0.0.0.15.dist-info/DESCRIPTION.rst
Homevee_Cloud-0.0.0.15.dist-info/METADATA
Homevee_Cloud-0.0.0.15.dist-info/RECORD
Homevee_Cloud-0.0.0.15.dist-info/WHEEL
Homevee_Cloud-0.0.0.15.dist-info/entry_points.txt
Homevee_Cloud-0.0.0.15.dist-info/metadata.json
Homevee_Cloud-0.0.0.15.dist-info/top_level.txt
