Metadata-Version: 2.0
Name: Homevee-Cloud
Version: 0.0.0.15
Summary: Dein neues Smarthome-System!
Home-page: https://github.com/homevee/homevee-cloud
Author: Homevee-Cloud
Author-email: support@homevee.de
License: UNKNOWN
Platform: UNKNOWN
Classifier: Programming Language :: Python :: 3.6
Classifier: License :: OSI Approved :: MIT License
Classifier: Operating System :: OS Independent
Requires-Dist: pyfcm
